[
    {
        "CNO":  "0001",
        "SEX":  "M",
        "CANDIDATE-NAME":  "ALMACHIUS MUKYANUZI",
        "AGGT":  "19",
        "DIV":  "II",
        "DETAILED-SUBJECTS":  "CIV:C;HIS:C;GEO:D;BIB:B;KIS:C;ENG:B;PHY:C;CHE:C;BIO:C;BAS:C"
    },
    {
        "CNO":  "0002",
        "SEX":  "M",
        "CANDIDATE-NAME":  "ANTIDIUS KAIJAGE",
        "AGGT":  "16",
        "DIV":  "I",
        "DETAILED-SUBJECTS":  "CIV:B;HIS:C;GEO:C;BIB:B;KIS:B;ENG:B;PHY:C;CHE:B;BIO:C;BAS:C"
    },
    {
        "CNO":  "0003",
        "SEX":  "M",
        "CANDIDATE-NAME":  "ANTIDIUS KAITU",
        "AGGT":  "15",
        "DIV":  "I",
        "DETAILED-SUBJECTS":  "CIV:C;HIS:B;GEO:C;BIB:A;KIS:B;ENG:B;PHY:B;CHE:C;BIO:C;BAS:C"
    },
    {
        "CNO":  "0004",
        "SEX":  "M",
        "CANDIDATE-NAME":  "ARISTIDES RWEBANGIRA",
        "AGGT":  "14",
        "DIV":  "I",
        "DETAILED-SUBJECTS":  "CIV:B;HIS:C;GEO:B;BIB:B;KIS:B;ENG:B;PHY:C;CHE:B;BIO:B;BAS:D"
    },
    {
        "CNO":  "0005",
        "SEX":  "M",
        "CANDIDATE-NAME":  "DERICK MWESIGA",
        "AGGT":  "14",
        "DIV":  "I",
        "DETAILED-SUBJECTS":  "CIV:A;HIS:B;GEO:D;BIB:B;KIS:C;ENG:B;PHY:C;CHE:B;BIO:B;BAS:D"
    },
    {
        "CNO":  "0006",
        "SEX":  "M",
        "CANDIDATE-NAME":  "FATIUS FARAJA",
        "AGGT":  "18",
        "DIV":  "II",
        "DETAILED-SUBJECTS":  "CIV:B;HIS:C;GEO:C;BIB:C;KIS:B;ENG:B;PHY:D;CHE:D;BIO:C;BAS:D"
    },
    {
        "CNO":  "0007",
        "SEX":  "M",
        "CANDIDATE-NAME":  "FRANK MUTEGEKI",
        "AGGT":  "17",
        "DIV":  "I",
        "DETAILED-SUBJECTS":  "CIV:B;HIS:C;GEO:C;BIB:A;KIS:C;ENG:B;PHY:D;CHE:D;BIO:C;BAS:C"
    },
    {
        "CNO":  "0008",
        "SEX":  "M",
        "CANDIDATE-NAME":  "IVO MULOKOZI",
        "AGGT":  "14",
        "DIV":  "I",
        "DETAILED-SUBJECTS":  "CIV:C;HIS:B;GEO:C;BIB:A;KIS:C;ENG:C;PHY:B;CHE:B;BIO:B;BAS:B"
    },
    {
        "CNO":  "0009",
        "SEX":  "M",
        "CANDIDATE-NAME":  "JOHN LUBUVA",
        "AGGT":  "11",
        "DIV":  "I",
        "DETAILED-SUBJECTS":  "CIV:B;HIS:C;GEO:B;BIB:A;KIS:B;ENG:B;PHY:A;CHE:A;BIO:B;BAS:B"
    },
    {
        "CNO":  "0010",
        "SEX":  "M",
        "CANDIDATE-NAME":  "LEONCE TINDIBAIHUKAHO",
        "AGGT":  "18",
        "DIV":  "II",
        "DETAILED-SUBJECTS":  "CIV:B;HIS:F;GEO:D;BIB:C;KIS:C;ENG:C;PHY:C;CHE:C;BIO:C;BAS:A"
    },
    {
        "CNO":  "0011",
        "SEX":  "M",
        "CANDIDATE-NAME":  "NELIUS RWIZA",
        "AGGT":  "14",
        "DIV":  "I",
        "DETAILED-SUBJECTS":  "CIV:B;HIS:B;GEO:C;BIB:A;KIS:B;ENG:B;PHY:C;CHE:C;BIO:B;BAS:C"
    },
    {
        "CNO":  "0012",
        "SEX":  "M",
        "CANDIDATE-NAME":  "REVOCATUS MWEMEZI",
        "AGGT":  "17",
        "DIV":  "I",
        "DETAILED-SUBJECTS":  "CIV:B;HIS:B;GEO:C;BIB:B;KIS:B;ENG:C;PHY:D;CHE:C;BIO:C;BAS:C"
    },
    {
        "CNO":  "0013",
        "SEX":  "M",
        "CANDIDATE-NAME":  "SIGISMUND MUJUNI",
        "AGGT":  "13",
        "DIV":  "I",
        "DETAILED-SUBJECTS":  "CIV:B;HIS:B;GEO:C;BIB:A;KIS:B;ENG:B;PHY:B;CHE:B;BIO:B;BAS:C"
    },
    {
        "CNO":  "0014",
        "SEX":  "M",
        "CANDIDATE-NAME":  "THEOTINUS RUGAIYAMU",
        "AGGT":  "13",
        "DIV":  "I",
        "DETAILED-SUBJECTS":  "CIV:B;HIS:B;GEO:C;BIB:A;KIS:B;ENG:B;PHY:B;CHE:B;BIO:B;BAS:C"
    }
]
