[
    {
        "CNO":  "P1306/0001",
        "SEX":  "F",
        "CANDIDATE-NAME":  "AMINA KHAMIS KOMBO",
        "AGGT":  "33",
        "DIV":  "IV",
        "DETAILED-SUBJECTS":  "CIV:F;HIST:F;GEO:F;E-D-KIISLAMU:D;KISW:F;ENGL:F;ARABIC:D"
    },
    {
        "CNO":  "P1306/0002",
        "SEX":  "F",
        "CANDIDATE-NAME":  "AMINA O MOH\u0027D",
        "AGGT":  "33",
        "DIV":  "IV",
        "DETAILED-SUBJECTS":  "CIV:F;GEO:F;E-D-KIISLAMU:D;KISW:F;ENGL:F;ARABIC:D;CHEM:F;BIO:F;B-MATH:F"
    },
    {
        "CNO":  "P1306/0003",
        "SEX":  "F",
        "CANDIDATE-NAME":  "AMINA SULEIMAN SALIM",
        "AGGT":  "34",
        "DIV":  "FLD",
        "DETAILED-SUBJECTS":  "CIV:F;HIST:F;GEO:F;E-D-KIISLAMU:F;KISW:F;ENGL:F;ARABIC:D;BIO:F;B-MATH:F"
    },
    {
        "CNO":  "P1306/0004",
        "SEX":  "F",
        "CANDIDATE-NAME":  "ARAFA M KHAMIS",
        "AGGT":  "33",
        "DIV":  "IV",
        "DETAILED-SUBJECTS":  "CIV:F;GEO:F;E-D-KIISLAMU:D;KISW:F;ENGL:F;ARABIC:D;CHEM:F;BIO:F;B-MATH:F"
    },
    {
        "CNO":  "P1306/0005",
        "SEX":  "F",
        "CANDIDATE-NAME":  "ASHA ABDALAH JUMA",
        "AGGT":  "-",
        "DIV":  "IV",
        "DETAILED-SUBJECTS":  "CIV:F;HIST:F;GEO:F;E-D-KIISLAMU:C;KISW:F;ENGL:F"
    },
    {
        "CNO":  "P1306/0006",
        "SEX":  "F",
        "CANDIDATE-NAME":  "ASHA K OMAR",
        "AGGT":  "34",
        "DIV":  "FLD",
        "DETAILED-SUBJECTS":  "CIV:F;E-D-KIISLAMU:D;KISW:F;ENGL:F;PHY:X;CHEM:F;BIO:F;B-MATH:F"
    },
    {
        "CNO":  "P1306/0007",
        "SEX":  "F",
        "CANDIDATE-NAME":  "ASHA M SHAALI",
        "AGGT":  "-",
        "DIV":  "FLD",
        "DETAILED-SUBJECTS":  "CIV:F;HIST:F;GEO:F;ENGL:X;ARABIC:D;CHEM:X;COMM:X;B-KEEPING:F"
    },
    {
        "CNO":  "P1306/0008",
        "SEX":  "F",
        "CANDIDATE-NAME":  "ASHA MW JUMA",
        "AGGT":  "33",
        "DIV":  "IV",
        "DETAILED-SUBJECTS":  "CIV:F;HIST:F;GEO:F;E-D-KIISLAMU:D;ENGL:F;ARABIC:X;BIO:F;B-MATH:F;COMM:F;B-KEEPING:D"
    },
    {
        "CNO":  "P1306/0009",
        "SEX":  "F",
        "CANDIDATE-NAME":  "ASIA R BAKAR",
        "AGGT":  "-",
        "DIV":  "FLD",
        "DETAILED-SUBJECTS":  "CIV:F;HIST:F;GEO:F;KISW:F;ENGL:F;B-MATH:F"
    },
    {
        "CNO":  "P1306/0010",
        "SEX":  "F",
        "CANDIDATE-NAME":  "ASMA H ALI",
        "AGGT":  "34",
        "DIV":  "FLD",
        "DETAILED-SUBJECTS":  "CIV:F;HIST:F;GEO:F;E-D-KIISLAMU:F;KISW:D;ENGL:X;ARABIC:F;BIO:F"
    },
    {
        "CNO":  "P1306/0011",
        "SEX":  "F",
        "CANDIDATE-NAME":  "BATULI D ALI",
        "AGGT":  "33",
        "DIV":  "IV",
        "DETAILED-SUBJECTS":  "CIV:F;GEO:F;E-D-KIISLAMU:D;KISW:F;ENGL:F;ARABIC:D;CHEM:F;BIO:X"
    },
    {
        "CNO":  "P1306/0012",
        "SEX":  "F",
        "CANDIDATE-NAME":  "BIKOMBO M VUAI",
        "AGGT":  "34",
        "DIV":  "FLD",
        "DETAILED-SUBJECTS":  "CIV:F;HIST:F;GEO:X;E-D-KIISLAMU:D;KISW:F;ENGL:X;ARABIC:F;BIO:F;B-KEEPING:F"
    },
    {
        "CNO":  "P1306/0013",
        "SEX":  "F",
        "CANDIDATE-NAME":  "BIMKUBWA A MOH\u0027D",
        "AGGT":  "31",
        "DIV":  "IV",
        "DETAILED-SUBJECTS":  "CIV:F;GEO:F;E-D-KIISLAMU:C;KISW:F;ARABIC:C;PHY:F;CHEM:F;B-MATH:F;COMM:X;B-KEEPING:F"
    },
    {
        "CNO":  "P1306/0014",
        "SEX":  "F",
        "CANDIDATE-NAME":  "BIMKUBWA A SALIM",
        "AGGT":  "35",
        "DIV":  "FLD",
        "DETAILED-SUBJECTS":  "CIV:F;KISW:F;ENGL:F;ARABIC:F;PHY:X;CHEM:F;BIO:F;B-MATH:F"
    },
    {
        "CNO":  "P1306/0015",
        "SEX":  "F",
        "CANDIDATE-NAME":  "BIMKUBWA U MAKAME",
        "AGGT":  "34",
        "DIV":  "FLD",
        "DETAILED-SUBJECTS":  "CIV:F;KISW:F;ENGL:F;ARABIC:D;CHEM:F;BIO:F;B-MATH:F;COMM:F;B-KEEPING:F"
    },
    {
        "CNO":  "P1306/0016",
        "SEX":  "F",
        "CANDIDATE-NAME":  "FADHILA M MUSSA",
        "AGGT":  "33",
        "DIV":  "IV",
        "DETAILED-SUBJECTS":  "CIV:F;GEO:F;E-D-KIISLAMU:C;KISW:F;ENGL:F;ARABIC:F;CHEM:F;B-MATH:F;ELECT;ENG;SC:X"
    },
    {
        "CNO":  "P1306/0017",
        "SEX":  "F",
        "CANDIDATE-NAME":  "FAT-HIYA O KOMBO",
        "AGGT":  "34",
        "DIV":  "FLD",
        "DETAILED-SUBJECTS":  "CIV:F;E-D-KIISLAMU:D;KISW:F;ENGL:F;ARABIC:F;CHEM:F;BIO:F"
    },
    {
        "CNO":  "P1306/0018",
        "SEX":  "F",
        "CANDIDATE-NAME":  "FATMA A MAKAME",
        "AGGT":  "-",
        "DIV":  "FLD",
        "DETAILED-SUBJECTS":  "CIV:F;HIST:F;GEO:F;KISW:F;ENGL:F;BIO:F"
    },
    {
        "CNO":  "P1306/0019",
        "SEX":  "F",
        "CANDIDATE-NAME":  "FATMA J AMIR",
        "AGGT":  "33",
        "DIV":  "IV",
        "DETAILED-SUBJECTS":  "CIV:F;HIST:F;GEO:F;E-D-KIISLAMU:D;KISW:F;ENGL:F;ARABIC:D;BIO:F;COMM:F;B-KEEPING:F"
    },
    {
        "CNO":  "P1306/0020",
        "SEX":  "F",
        "CANDIDATE-NAME":  "FATMA J MAKAME",
        "AGGT":  "35",
        "DIV":  "FLD",
        "DETAILED-SUBJECTS":  "CIV:F;HIST:F;E-D-KIISLAMU:F;KISW:F;ENGL:F;BIO:X;B-MATH:F;COMM:F;B-KEEPING:F"
    },
    {
        "CNO":  "P1306/0021",
        "SEX":  "F",
        "CANDIDATE-NAME":  "FATMA KH JUMA",
        "AGGT":  "35",
        "DIV":  "FLD",
        "DETAILED-SUBJECTS":  "CIV:F;HIST:F;E-D-KIISLAMU:F;KISW:F;ENGL:F;ARABIC:X;BIO:F;COMM:F;B-KEEPING:F"
    },
    {
        "CNO":  "P1306/0022",
        "SEX":  "F",
        "CANDIDATE-NAME":  "FATMA M MWADINI",
        "AGGT":  "-",
        "DIV":  "FLD",
        "DETAILED-SUBJECTS":  "CIV:F;HIST:F;E-D-KIISLAMU:F;KISW:F;ENG;SC:F;B-KEEPING:F"
    },
    {
        "CNO":  "P1306/0023",
        "SEX":  "F",
        "CANDIDATE-NAME":  "FATUMA FAKI MOHAMED",
        "AGGT":  "33",
        "DIV":  "IV",
        "DETAILED-SUBJECTS":  "CIV:F;HIST:F;E-D-KIISLAMU:C;KISW:F;ENGL:F;ARABIC:F;CHEM:F;BIO:F;B-KEEPING:F"
    },
    {
        "CNO":  "P1306/0024",
        "SEX":  "F",
        "CANDIDATE-NAME":  "HADIA S SAID",
        "AGGT":  "35",
        "DIV":  "FLD",
        "DETAILED-SUBJECTS":  "CIV:F;HIST:F;GEO:F;E-D-KIISLAMU:F;KISW:F;ENGL:F;BIO:F;COMM:F;B-KEEPING:F"
    },
    {
        "CNO":  "P1306/0025",
        "SEX":  "F",
        "CANDIDATE-NAME":  "JAMILA A JUMA",
        "AGGT":  "33",
        "DIV":  "IV",
        "DETAILED-SUBJECTS":  "CIV:F;GEO:F;KISW:F;ENGL:F;ARABIC:C;CHEM:F;BIO:F;B-MATH:F;COMM:F;B-KEEPING:F"
    },
    {
        "CNO":  "P1306/0026",
        "SEX":  "F",
        "CANDIDATE-NAME":  "KAMARIA A KHALID",
        "AGGT":  "34",
        "DIV":  "FLD",
        "DETAILED-SUBJECTS":  "CIV:F;GEO:F;E-D-KIISLAMU:D;KISW:F;ENGL:F;PHY:F;CHEM:F;BIO:F;B-MATH:F"
    },
    {
        "CNO":  "P1306/0027",
        "SEX":  "F",
        "CANDIDATE-NAME":  "KHADIJA A BAKARI",
        "AGGT":  "34",
        "DIV":  "FLD",
        "DETAILED-SUBJECTS":  "CIV:F;GEO:F;E-D-KIISLAMU:D;KISW:F;ENGL:F;ARABIC:F;PHY:F;CHEM:F;BIO:F;ENG;SC:F"
    },
    {
        "CNO":  "P1306/0028",
        "SEX":  "F",
        "CANDIDATE-NAME":  "KHADIJA R ALI",
        "AGGT":  "34",
        "DIV":  "FLD",
        "DETAILED-SUBJECTS":  "CIV:F;HIST:F;GEO:F;E-D-KIISLAMU:F;KISW:F;ENGL:F;ARABIC:D;BIO:F"
    },
    {
        "CNO":  "P1306/0029",
        "SEX":  "F",
        "CANDIDATE-NAME":  "KIDAWA OMAR MAKAME",
        "AGGT":  "35",
        "DIV":  "FLD",
        "DETAILED-SUBJECTS":  "CIV:F;HIST:F;E-D-KIISLAMU:F;KISW:F;ENGL:F;ARABIC:F;COMM:F;B-KEEPING:F"
    },
    {
        "CNO":  "P1306/0030",
        "SEX":  "F",
        "CANDIDATE-NAME":  "MAFUNDA ALI BAKAR",
        "AGGT":  "-",
        "DIV":  "IV",
        "DETAILED-SUBJECTS":  "CIV:F;HIST:X;GEO:F;E-D-KIISLAMU:D;KISW:F;ENGL:X;ARABIC:D"
    },
    {
        "CNO":  "P1306/0031",
        "SEX":  "F",
        "CANDIDATE-NAME":  "MARIAM M JUMA",
        "AGGT":  "34",
        "DIV":  "FLD",
        "DETAILED-SUBJECTS":  "CIV:F;HIST:F;GEO:F;E-D-KIISLAMU:D;KISW:F;ENGL:F;COMM:X;B-KEEPING:F"
    },
    {
        "CNO":  "P1306/0032",
        "SEX":  "F",
        "CANDIDATE-NAME":  "MAUA M SEIF",
        "AGGT":  "34",
        "DIV":  "FLD",
        "DETAILED-SUBJECTS":  "CIV:F;GEO:F;KISW:F;ENGL:F;ARABIC:D;PHY:F;CHEM:F;BIO:F;ENG;SC:F;B-KEEPING:F"
    },
    {
        "CNO":  "P1306/0033",
        "SEX":  "F",
        "CANDIDATE-NAME":  "MAYMUNA M ABDULLA",
        "AGGT":  "34",
        "DIV":  "FLD",
        "DETAILED-SUBJECTS":  "CIV:F;HIST:F;GEO:F;E-D-KIISLAMU:F;KISW:F;ENGL:F;ARABIC:D;COMM:F;B-KEEPING:F"
    },
    {
        "CNO":  "P1306/0034",
        "SEX":  "F",
        "CANDIDATE-NAME":  "MEYUU A NASSOR",
        "AGGT":  "-",
        "DIV":  "IV",
        "DETAILED-SUBJECTS":  "CIV:F;HIST:F;GEO:F;E-D-KIISLAMU:C;KISW:F;ENGL:F"
    },
    {
        "CNO":  "P1306/0035",
        "SEX":  "F",
        "CANDIDATE-NAME":  "MISHI KOMBO JUMA",
        "AGGT":  "35",
        "DIV":  "FLD",
        "DETAILED-SUBJECTS":  "CIV:F;HIST:F;GEO:F;E-D-KIISLAMU:F;KISW:F;ENGL:F;ARABIC:F"
    },
    {
        "CNO":  "P1306/0036",
        "SEX":  "F",
        "CANDIDATE-NAME":  "MTUMWA NY OTHMAN",
        "AGGT":  "34",
        "DIV":  "FLD",
        "DETAILED-SUBJECTS":  "CIV:F;HIST:F;GEO:F;E-D-KIISLAMU:D;KISW:F;ENGL:F;CHEM:F;BIO:F;COMM:F;B-KEEPING:F"
    },
    {
        "CNO":  "P1306/0037",
        "SEX":  "F",
        "CANDIDATE-NAME":  "MWAJUMA A OTHMAN",
        "AGGT":  "32",
        "DIV":  "IV",
        "DETAILED-SUBJECTS":  "CIV:F;HIST:F;GEO:X;E-D-KIISLAMU:C;ENGL:F;ARABIC:D;CHEM:F;BIO:F;COMM:F;B-KEEPING:F"
    },
    {
        "CNO":  "P1306/0038",
        "SEX":  "F",
        "CANDIDATE-NAME":  "MWAMIZE A MOHAMED",
        "AGGT":  "34",
        "DIV":  "FLD",
        "DETAILED-SUBJECTS":  "GEO:F;E-D-KIISLAMU:F;KISW:F;ENGL:F;ARABIC:D;PHY:F;CHEM:F;BIO:F;ENG;SC:F;B-KEEPING:F"
    },
    {
        "CNO":  "P1306/0039",
        "SEX":  "F",
        "CANDIDATE-NAME":  "NAIMA K JUMA",
        "AGGT":  "35",
        "DIV":  "FLD",
        "DETAILED-SUBJECTS":  "CIV:F;GEO:F;KISW:F;ENGL:F;ARABIC:F;CHEM:F;BIO:F"
    },
    {
        "CNO":  "P1306/0040",
        "SEX":  "F",
        "CANDIDATE-NAME":  "NUSURA A ALI",
        "AGGT":  "-",
        "DIV":  "FLD",
        "DETAILED-SUBJECTS":  "CIV:F;HIST:F;GEO:F;E-D-KIISLAMU:D;KISW:F;ENGL:F;B-MATH:X"
    },
    {
        "CNO":  "P1306/0041",
        "SEX":  "F",
        "CANDIDATE-NAME":  "RAMLA A ABBASI",
        "AGGT":  "35",
        "DIV":  "FLD",
        "DETAILED-SUBJECTS":  "CIV:F;HIST:F;E-D-KIISLAMU:F;KISW:F;ENGL:F;BIO:F;B-MATH:F;COMM:F;B-KEEPING:F"
    },
    {
        "CNO":  "P1306/0042",
        "SEX":  "F",
        "CANDIDATE-NAME":  "RAYA SH OMARI",
        "AGGT":  "35",
        "DIV":  "FLD",
        "DETAILED-SUBJECTS":  "CIV:F;E-D-KIISLAMU:F;KISW:F;ENGL:F;CHEM:F;BIO:F;B-MATH:F;COMM:X;B-KEEPING:F"
    },
    {
        "CNO":  "P1306/0043",
        "SEX":  "F",
        "CANDIDATE-NAME":  "REHEMA KH KASSIM",
        "AGGT":  "-",
        "DIV":  "FLD",
        "DETAILED-SUBJECTS":  "CIV:F;HIST:F;E-D-KIISLAMU:D;KISW:F;ENG;SC:F;B-KEEPING:F"
    },
    {
        "CNO":  "P1306/0044",
        "SEX":  "F",
        "CANDIDATE-NAME":  "RUKIA M ABBASS",
        "AGGT":  "31",
        "DIV":  "IV",
        "DETAILED-SUBJECTS":  "CIV:F;E-D-KIISLAMU:C;KISW:D;ENGL:F;ARABIC:D;PHY:X;CHEM:X;BIO:F;B-MATH:F"
    },
    {
        "CNO":  "P1306/0045",
        "SEX":  "F",
        "CANDIDATE-NAME":  "SALMA J AMIRI",
        "AGGT":  "-",
        "DIV":  "IV",
        "DETAILED-SUBJECTS":  "CIV:F;HIST:F;GEO:F;E-D-KIISLAMU:C;ENGL:F"
    },
    {
        "CNO":  "P1306/0046",
        "SEX":  "F",
        "CANDIDATE-NAME":  "SAUMU H KHAMIS",
        "AGGT":  "33",
        "DIV":  "IV",
        "DETAILED-SUBJECTS":  "CIV:F;E-D-KIISLAMU:F;KISW:F;ENGL:F;ARABIC:D;PHY:X;CHEM:D;BIO:F;B-MATH:F"
    },
    {
        "CNO":  "P1306/0047",
        "SEX":  "F",
        "CANDIDATE-NAME":  "SHUNUNA S JUMA",
        "AGGT":  "35",
        "DIV":  "FLD",
        "DETAILED-SUBJECTS":  "CIV:F;HIST:F;GEO:F;KISW:F;ENGL:F;COMM:F;B-KEEPING:F"
    },
    {
        "CNO":  "P1306/0048",
        "SEX":  "F",
        "CANDIDATE-NAME":  "SITI A MAKAME",
        "AGGT":  "-",
        "DIV":  "FLD",
        "DETAILED-SUBJECTS":  "CIV:F;HIST:F;E-D-KIISLAMU:F;KISW:F;ENG;SC:F;B-KEEPING:F"
    },
    {
        "CNO":  "P1306/0049",
        "SEX":  "F",
        "CANDIDATE-NAME":  "SUBIRA J KASSIM",
        "AGGT":  "33",
        "DIV":  "IV",
        "DETAILED-SUBJECTS":  "CIV:F;HIST:F;E-D-KIISLAMU:C;KISW:F;CHEM:F;B-MATH:F;COMM:F;B-KEEPING:F"
    },
    {
        "CNO":  "P1306/0050",
        "SEX":  "F",
        "CANDIDATE-NAME":  "TATU A KHAMIS",
        "AGGT":  "33",
        "DIV":  "IV",
        "DETAILED-SUBJECTS":  "CIV:F;HIST:F;GEO:F;E-D-KIISLAMU:C;ENGL:F;CHEM:F;BIO:F;B-MATH:F;COMM:F;B-KEEPING:F"
    },
    {
        "CNO":  "P1306/0051",
        "SEX":  "F",
        "CANDIDATE-NAME":  "TATU A MOH\u0027D",
        "AGGT":  "34",
        "DIV":  "FLD",
        "DETAILED-SUBJECTS":  "CIV:F;GEO:F;KISW:F;ENGL:F;ARABIC:D;CHEM:F;BIO:F;B-MATH:F;COMM:X;B-KEEPING:F"
    },
    {
        "CNO":  "P1306/0052",
        "SEX":  "F",
        "CANDIDATE-NAME":  "UMU-KULTHUM S ABEID",
        "AGGT":  "-",
        "DIV":  "FLD",
        "DETAILED-SUBJECTS":  "CIV:F;HIST:F;E-D-KIISLAMU:F;KISW:F;ENGL:F;COMM:F"
    },
    {
        "CNO":  "P1306/0053",
        "SEX":  "F",
        "CANDIDATE-NAME":  "ZAINA KOMBO JUMA",
        "AGGT":  "34",
        "DIV":  "FLD",
        "DETAILED-SUBJECTS":  "CIV:F;HIST:F;GEO:F;E-D-KIISLAMU:D;KISW:F;ENGL:F;ARABIC:F"
    },
    {
        "CNO":  "P1306/0054",
        "SEX":  "F",
        "CANDIDATE-NAME":  "ZUBEDA A MJEMBA",
        "AGGT":  "33",
        "DIV":  "IV",
        "DETAILED-SUBJECTS":  "CIV:F;HIST:F;GEO:F;E-D-KIISLAMU:C;ENGL:F;CHEM:F;COMM:F;B-KEEPING:F"
    },
    {
        "CNO":  "P1306/0055",
        "SEX":  "F",
        "CANDIDATE-NAME":  "ZUHURA S. MGENI",
        "AGGT":  "35",
        "DIV":  "FLD",
        "DETAILED-SUBJECTS":  "CIV:F;HIST:F;GEO:F;E-D-KIISLAMU:F;KISW:F;ENGL:F;ARABIC:F"
    },
    {
        "CNO":  "P1306/0056",
        "SEX":  "F",
        "CANDIDATE-NAME":  "ZUWENA ALI MZEE",
        "AGGT":  "34",
        "DIV":  "FLD",
        "DETAILED-SUBJECTS":  "CIV:F;HIST:F;GEO:F;E-D-KIISLAMU:D;KISW:F;ENGL:F;ARABIC:F"
    },
    {
        "CNO":  "P1306/0057",
        "SEX":  "F",
        "CANDIDATE-NAME":  "ZUWENA FAKI IDDI",
        "AGGT":  "33",
        "DIV":  "IV",
        "DETAILED-SUBJECTS":  "CIV:F;HIST:F;GEO:F;E-D-KIISLAMU:C;KISW:F;ENGL:F;ARABIC:F"
    },
    {
        "CNO":  "P1306/0058",
        "SEX":  "F",
        "CANDIDATE-NAME":  "ZUWENA O SHAALI",
        "AGGT":  "32",
        "DIV":  "IV",
        "DETAILED-SUBJECTS":  "CIV:F;HIST:F;E-D-KIISLAMU:C;KISW:F;ENGL:F;ARABIC:D;BIO:F;B-MATH:F;B-KEEPING:F"
    },
    {
        "CNO":  "P1306/0059",
        "SEX":  "M",
        "CANDIDATE-NAME":  "ABDULHALIM O BAKAR",
        "AGGT":  "34",
        "DIV":  "FLD",
        "DETAILED-SUBJECTS":  "CIV:F;HIST:F;E-D-KIISLAMU:D;KISW:F;ENGL:F;CHEM:F;BIO:F;COMM:X;B-KEEPING:F"
    },
    {
        "CNO":  "P1306/0060",
        "SEX":  "M",
        "CANDIDATE-NAME":  "ALI M MAALIM",
        "AGGT":  "34",
        "DIV":  "FLD",
        "DETAILED-SUBJECTS":  "CIV:F;HIST:F;GEO:F;E-D-KIISLAMU:D;KISW:F;ENGL:F;CHEM:X;BIO:F;COMM:X;B-KEEPING:F"
    },
    {
        "CNO":  "P1306/0061",
        "SEX":  "M",
        "CANDIDATE-NAME":  "ALI M OMAR",
        "AGGT":  "33",
        "DIV":  "IV",
        "DETAILED-SUBJECTS":  "CIV:F;E-D-KIISLAMU:D;KISW:F;ENGL:F;ARABIC:D;PHY:X;CHEM:F;BIO:F;COMM:X;B-KEEPING:F"
    },
    {
        "CNO":  "P1306/0062",
        "SEX":  "M",
        "CANDIDATE-NAME":  "AWESU M ALI",
        "AGGT":  "34",
        "DIV":  "FLD",
        "DETAILED-SUBJECTS":  "CIV:F;HIST:F;E-D-KIISLAMU:D;KISW:F;ENGL:F;BIO:X;B-MATH:X;COMM:F;B-KEEPING:F"
    },
    {
        "CNO":  "P1306/0063",
        "SEX":  "M",
        "CANDIDATE-NAME":  "BAISHE M ISSA",
        "AGGT":  "35",
        "DIV":  "FLD",
        "DETAILED-SUBJECTS":  "CIV:F;GEO:F;E-D-KIISLAMU:X;KISW:F;ENGL:F;ARABIC:X;PHY:X;CHEM:F;ENG;SC:F;B-MATH:F"
    },
    {
        "CNO":  "P1306/0064",
        "SEX":  "M",
        "CANDIDATE-NAME":  "HAJI MW HAJI",
        "AGGT":  "-",
        "DIV":  "FLD",
        "DETAILED-SUBJECTS":  "CIV:F;GEO:F;E-D-KIISLAMU:F;KISW:F;ENGL:F"
    },
    {
        "CNO":  "P1306/0065",
        "SEX":  "M",
        "CANDIDATE-NAME":  "HAMZA M SHAAME",
        "AGGT":  "35",
        "DIV":  "FLD",
        "DETAILED-SUBJECTS":  "CIV:F;KISW:F;ENGL:F;ARABIC:F;CHEM:F;B-MATH:F;COMM:X;B-KEEPING:F"
    },
    {
        "CNO":  "P1306/0066",
        "SEX":  "M",
        "CANDIDATE-NAME":  "HASHIM A RAJAB",
        "AGGT":  "35",
        "DIV":  "FLD",
        "DETAILED-SUBJECTS":  "CIV:F;HIST:F;GEO:F;KISW:F;ENGL:F;ARABIC:F;B-MATH:F;COMM:X;B-KEEPING:F"
    },
    {
        "CNO":  "P1306/0067",
        "SEX":  "M",
        "CANDIDATE-NAME":  "HASSAN KH JUMA",
        "AGGT":  "-",
        "DIV":  "ABS",
        "DETAILED-SUBJECTS":  "CIV:X;GEO:X;KISW:X;ENGL:X;ARABIC:X;PHY:X;CHEM:X;B-MATH:X;COMM:X;B-KEEPING:X"
    },
    {
        "CNO":  "P1306/0068",
        "SEX":  "M",
        "CANDIDATE-NAME":  "HASSAN R KOMBO",
        "AGGT":  "34",
        "DIV":  "FLD",
        "DETAILED-SUBJECTS":  "CIV:F;HIST:F;GEO:F;E-D-KIISLAMU:D;KISW:F;ENGL:F;ARABIC:F;CHEM:X;BIO:F;B-KEEPING:F"
    },
    {
        "CNO":  "P1306/0069",
        "SEX":  "M",
        "CANDIDATE-NAME":  "JAFAR J ALI",
        "AGGT":  "34",
        "DIV":  "FLD",
        "DETAILED-SUBJECTS":  "CIV:F;E-D-KIISLAMU:D;KISW:F;ENGL:F;PHY:F;CHEM:F;BIO:F"
    },
    {
        "CNO":  "P1306/0070",
        "SEX":  "M",
        "CANDIDATE-NAME":  "JUMA KH SHAIBU",
        "AGGT":  "35",
        "DIV":  "FLD",
        "DETAILED-SUBJECTS":  "CIV:F;HIST:F;GEO:F;KISW:F;ENGL:F;ARABIC:F;COMM:X;B-KEEPING:F"
    },
    {
        "CNO":  "P1306/0071",
        "SEX":  "M",
        "CANDIDATE-NAME":  "JUMA K JUMA",
        "AGGT":  "-",
        "DIV":  "FLD",
        "DETAILED-SUBJECTS":  "CIV:F;GEO:F;E-D-KIISLAMU:D;KISW:F;CHEM:F;BIO:F"
    },
    {
        "CNO":  "P1306/0072",
        "SEX":  "M",
        "CANDIDATE-NAME":  "JUMA M JUMA",
        "AGGT":  "33",
        "DIV":  "IV",
        "DETAILED-SUBJECTS":  "CIV:F;HIST:F;GEO:F;E-D-KIISLAMU:D;KISW:F;ENGL:F;ARABIC:D;BIO:F"
    },
    {
        "CNO":  "P1306/0073",
        "SEX":  "M",
        "CANDIDATE-NAME":  "KASSIM M JUMA",
        "AGGT":  "34",
        "DIV":  "FLD",
        "DETAILED-SUBJECTS":  "CIV:F;HIST:F;GEO:F;E-D-KIISLAMU:D;KISW:F;ENGL:F;COMM:X;B-KEEPING:F"
    },
    {
        "CNO":  "P1306/0074",
        "SEX":  "M",
        "CANDIDATE-NAME":  "KASSIM M MSHENGA",
        "AGGT":  "34",
        "DIV":  "FLD",
        "DETAILED-SUBJECTS":  "CIV:F;HIST:F;GEO:F;E-D-KIISLAMU:D;KISW:F;ENGL:F;CHEM:F;BIO:X;COMM:X;B-KEEPING:F"
    },
    {
        "CNO":  "P1306/0075",
        "SEX":  "M",
        "CANDIDATE-NAME":  "KHAMIS BAKAR KHAMIS",
        "AGGT":  "35",
        "DIV":  "FLD",
        "DETAILED-SUBJECTS":  "CIV:F;HIST:F;GEO:F;E-D-KIISLAMU:F;KISW:F;ENGL:F;ARABIC:F"
    },
    {
        "CNO":  "P1306/0076",
        "SEX":  "M",
        "CANDIDATE-NAME":  "KHAMIS M MZEE",
        "AGGT":  "-",
        "DIV":  "FLD",
        "DETAILED-SUBJECTS":  "KISW:F;ARABIC:F;CHEM:F;ENG;SC:X;COMM:X;B-KEEPING:F"
    },
    {
        "CNO":  "P1306/0077",
        "SEX":  "M",
        "CANDIDATE-NAME":  "KHATIB M OMAR",
        "AGGT":  "35",
        "DIV":  "FLD",
        "DETAILED-SUBJECTS":  "CIV:F;HIST:F;GEO:F;E-D-KIISLAMU:F;KISW:F;ENGL:F;ARABIC:F;CHEM:F;BIO:F;B-MATH:F"
    },
    {
        "CNO":  "P1306/0078",
        "SEX":  "M",
        "CANDIDATE-NAME":  "KOMBO M IDDI",
        "AGGT":  "-",
        "DIV":  "FLD",
        "DETAILED-SUBJECTS":  "CIV:X;GEO:F;E-D-KIISLAMU:D;KISW:F;ENGL:F;ARABIC:X;PHY:F;BIO:F;B-MATH:X;B-KEEPING:X"
    },
    {
        "CNO":  "P1306/0079",
        "SEX":  "M",
        "CANDIDATE-NAME":  "KOMBO S KOMBO",
        "AGGT":  "34",
        "DIV":  "FLD",
        "DETAILED-SUBJECTS":  "CIV:F;HIST:F;E-D-KIISLAMU:D;KISW:F;ENGL:F;ARABIC:F;BIO:F;B-MATH:F;COMM:F;B-KEEPING:F"
    },
    {
        "CNO":  "P1306/0080",
        "SEX":  "M",
        "CANDIDATE-NAME":  "MASSOUD A MAKAME",
        "AGGT":  "33",
        "DIV":  "IV",
        "DETAILED-SUBJECTS":  "CIV:F;GEO:F;KISW:F;ENGL:F;ARABIC:C;PHY:F;CHEM:F;BIO:F;B-MATH:F;B-KEEPING:F"
    },
    {
        "CNO":  "P1306/0081",
        "SEX":  "M",
        "CANDIDATE-NAME":  "MOH\u0027D A KOMBO",
        "AGGT":  "35",
        "DIV":  "FLD",
        "DETAILED-SUBJECTS":  "CIV:F;GEO:F;KISW:F;ENGL:F;PHY:F;CHEM:F;BIO:F;B-MATH:F"
    },
    {
        "CNO":  "P1306/0082",
        "SEX":  "M",
        "CANDIDATE-NAME":  "MOH\u0027D A MOH\u0027D",
        "AGGT":  "35",
        "DIV":  "FLD",
        "DETAILED-SUBJECTS":  "CIV:F;E-D-KIISLAMU:F;KISW:F;ENGL:F;PHY:F;CHEM:F;BIO:F"
    },
    {
        "CNO":  "P1306/0083",
        "SEX":  "M",
        "CANDIDATE-NAME":  "MOH\u0027D F MOH\u0027D",
        "AGGT":  "34",
        "DIV":  "FLD",
        "DETAILED-SUBJECTS":  "CIV:F;HIST:F;GEO:F;KISW:F;ENGL:F;ARABIC:D;CHEM:F;BIO:F;COMM:F;B-KEEPING:F"
    },
    {
        "CNO":  "P1306/0084",
        "SEX":  "M",
        "CANDIDATE-NAME":  "MUSSA J. DADI",
        "AGGT":  "35",
        "DIV":  "FLD",
        "DETAILED-SUBJECTS":  "CIV:F;HIST:F;GEO:F;E-D-KIISLAMU:F;KISW:F;ENGL:F;ARABIC:F"
    },
    {
        "CNO":  "P1306/0085",
        "SEX":  "M",
        "CANDIDATE-NAME":  "MWALIMU U MAKAME",
        "AGGT":  "34",
        "DIV":  "FLD",
        "DETAILED-SUBJECTS":  "CIV:F;HIST:F;GEO:F;E-D-KIISLAMU:D;KISW:F;ENGL:F;ARABIC:F;BIO:F;COMM:F;B-KEEPING:F"
    },
    {
        "CNO":  "P1306/0086",
        "SEX":  "M",
        "CANDIDATE-NAME":  "OMAR A HAJI",
        "AGGT":  "34",
        "DIV":  "FLD",
        "DETAILED-SUBJECTS":  "CIV:F;HIST:F;GEO:F;E-D-KIISLAMU:D;KISW:F;ENGL:F;ARABIC:F"
    },
    {
        "CNO":  "P1306/0087",
        "SEX":  "M",
        "CANDIDATE-NAME":  "OMARI M BADRU",
        "AGGT":  "35",
        "DIV":  "FLD",
        "DETAILED-SUBJECTS":  "CIV:F;HIST:F;GEO:F;KISW:F;ENGL:F;ARABIC:F;CHEM:F;BIO:F;COMM:F;B-KEEPING:F"
    },
    {
        "CNO":  "P1306/0088",
        "SEX":  "M",
        "CANDIDATE-NAME":  "OMAR KH KOMBO",
        "AGGT":  "35",
        "DIV":  "FLD",
        "DETAILED-SUBJECTS":  "CIV:F;HIST:F;GEO:F;KISW:F;ENGL:F;ARABIC:F;CHEM:F;BIO:F;B-MATH:F"
    },
    {
        "CNO":  "P1306/0089",
        "SEX":  "M",
        "CANDIDATE-NAME":  "OTHMAN M IDDI",
        "AGGT":  "-",
        "DIV":  "IV",
        "DETAILED-SUBJECTS":  "HIST:F;E-D-KIISLAMU:C;KISW:F;ENGL:F;ARABIC:D;BIO:F;B-KEEPING:X"
    },
    {
        "CNO":  "P1306/0090",
        "SEX":  "M",
        "CANDIDATE-NAME":  "RAJAB J MOH\u0027D",
        "AGGT":  "-",
        "DIV":  "FLD",
        "DETAILED-SUBJECTS":  "CIV:F;GEO:F;E-D-KIISLAMU:D;KISW:F;PHY:X;CHEM:F;BIO:F;ENG;SC:X;B-MATH:X;B-KEEPING:X"
    },
    {
        "CNO":  "P1306/0091",
        "SEX":  "M",
        "CANDIDATE-NAME":  "RAMADHANI A MAKAME",
        "AGGT":  "-",
        "DIV":  "FLD",
        "DETAILED-SUBJECTS":  "CIV:F;HIST:F;GEO:X;KISW:F;ARABIC:F;BIO:X;B-MATH:X;COMM:X;B-KEEPING:F"
    },
    {
        "CNO":  "P1306/0092",
        "SEX":  "M",
        "CANDIDATE-NAME":  "SAID MASSOUD ALI",
        "AGGT":  "34",
        "DIV":  "FLD",
        "DETAILED-SUBJECTS":  "CIV:F;HIST:F;E-D-KIISLAMU:D;KISW:F;ENGL:F;ARABIC:F;B-MATH:F;COMM:F;B-KEEPING:F"
    },
    {
        "CNO":  "P1306/0093",
        "SEX":  "M",
        "CANDIDATE-NAME":  "SHARIFU A HAMADI",
        "AGGT":  "33",
        "DIV":  "IV",
        "DETAILED-SUBJECTS":  "CIV:F;HIST:D;KISW:F;ENGL:F;ARABIC:D;CHEM:X;BIO:F;B-MATH:F"
    },
    {
        "CNO":  "P1306/0094",
        "SEX":  "M",
        "CANDIDATE-NAME":  "SHEIKHAN A SHEIKAN",
        "AGGT":  "33",
        "DIV":  "IV",
        "DETAILED-SUBJECTS":  "CIV:F;HIST:F;GEO:F;E-D-KIISLAMU:D;KISW:F;ENGL:F;ARABIC:D;COMM:X;B-KEEPING:X"
    },
    {
        "CNO":  "P1306/0095",
        "SEX":  "M",
        "CANDIDATE-NAME":  "USSI I SAID",
        "AGGT":  "-",
        "DIV":  "IV",
        "DETAILED-SUBJECTS":  "CIV:F;HIST:F;GEO:F;KISW:F;ENGL:F;ARABIC:C;CHEM:X;BIO:X;COMM:X;B-KEEPING:X"
    },
    {
        "CNO":  "P1306/0096",
        "SEX":  "M",
        "CANDIDATE-NAME":  "ZUBEIR O DAUDI",
        "AGGT":  "35",
        "DIV":  "FLD",
        "DETAILED-SUBJECTS":  "CIV:F;HIST:F;E-D-KIISLAMU:F;KISW:F;ENGL:F;CHEM:F;COMM:F;B-KEEPING:F"
    }
]
