[
    {
        "CNO":  "0001",
        "SEX":  "M",
        "CANDIDATE-NAME":  "ADOLPHUS MUSHUMBUSI",
        "AGGT":  "14",
        "DIV":  "I",
        "DETAILED-SUBJECTS":  "CIV:D;HIS:C;GEO:B;BIB:A;KIS:A;ENG:A;PHY:C;CHE:C;BIO:D;BAS:C"
    },
    {
        "CNO":  "0002",
        "SEX":  "M",
        "CANDIDATE-NAME":  "ALDO A KAMUGISHA",
        "AGGT":  "10",
        "DIV":  "I",
        "DETAILED-SUBJECTS":  "CIV:C;HIS:B;GEO:A;BIB:B;KIS:A;ENG:A;PHY:C;CHE:A;BIO:C;BAS:B"
    },
    {
        "CNO":  "0003",
        "SEX":  "M",
        "CANDIDATE-NAME":  "ALMACHIUS MWEYENDEZI",
        "AGGT":  "26",
        "DIV":  "IV",
        "DETAILED-SUBJECTS":  "CIV:C;HIS:F;GEO:D;BIB:D;KIS:C;ENG:D;PHY:F;CHE:D;BIO:F;BAS:D"
    },
    {
        "CNO":  "0004",
        "SEX":  "M",
        "CANDIDATE-NAME":  "ARNOLD RUTAKOMERWA",
        "AGGT":  "19",
        "DIV":  "III",
        "DETAILED-SUBJECTS":  "CIV:C;HIS:B;GEO:D;BIB:B;KIS:B;ENG:B;PHY:D;CHE:F;BIO:D;BAS:F"
    },
    {
        "CNO":  "0005",
        "SEX":  "M",
        "CANDIDATE-NAME":  "AVITUS RUGAKINGIRA",
        "AGGT":  "15",
        "DIV":  "I",
        "DETAILED-SUBJECTS":  "CIV:C;HIS:C;GEO:B;BIB:A;KIS:A;ENG:B;PHY:C;CHE:C;BIO:C;BAS:D"
    },
    {
        "CNO":  "0006",
        "SEX":  "M",
        "CANDIDATE-NAME":  "BENEDICT KWEYAMBA",
        "AGGT":  "20",
        "DIV":  "III",
        "DETAILED-SUBJECTS":  "CIV:C;HIS:D;GEO:C;BIB:B;KIS:D;ENG:C;PHY:C;CHE:C;BIO:C;BAS:F"
    },
    {
        "CNO":  "0007",
        "SEX":  "M",
        "CANDIDATE-NAME":  "DEUSDEDITI MUFURUKI",
        "AGGT":  "13",
        "DIV":  "I",
        "DETAILED-SUBJECTS":  "CIV:C;HIS:B;GEO:C;BIB:A;KIS:A;ENG:A;PHY:C;CHE:C;BIO:B;BAS:C"
    },
    {
        "CNO":  "0008",
        "SEX":  "M",
        "CANDIDATE-NAME":  "EGIDIUS KAMANYI",
        "AGGT":  "15",
        "DIV":  "I",
        "DETAILED-SUBJECTS":  "CIV:C;HIS:B;GEO:C;BIB:B;KIS:A;ENG:A;PHY:C;CHE:D;BIO:C;BAS:D"
    },
    {
        "CNO":  "0009",
        "SEX":  "M",
        "CANDIDATE-NAME":  "ELIAS MAKOYE",
        "AGGT":  "29",
        "DIV":  "IV",
        "DETAILED-SUBJECTS":  "CIV:D;HIS:F;GEO:D;BIB:C;KIS:D;ENG:D;PHY:X;CHE:X;BIO:F;BAS:F"
    },
    {
        "CNO":  "0010",
        "SEX":  "M",
        "CANDIDATE-NAME":  "ELIGIUS MUGANYIZI",
        "AGGT":  "11",
        "DIV":  "I",
        "DETAILED-SUBJECTS":  "CIV:B;HIS:B;GEO:A;BIB:B;KIS:B;ENG:A;PHY:A;CHE:B;BIO:C;BAS:B"
    },
    {
        "CNO":  "0011",
        "SEX":  "M",
        "CANDIDATE-NAME":  "ERICUS SHUMBUSHO",
        "AGGT":  "14",
        "DIV":  "I",
        "DETAILED-SUBJECTS":  "CIV:C;HIS:A;GEO:B;BIB:B;KIS:C;ENG:A;PHY:B;CHE:C;BIO:C;BAS:C"
    },
    {
        "CNO":  "0012",
        "SEX":  "M",
        "CANDIDATE-NAME":  "LATINUS MULOKOZI",
        "AGGT":  "17",
        "DIV":  "III",
        "DETAILED-SUBJECTS":  "CIV:D;HIS:C;GEO:C;BIB:B;KIS:A;ENG:B;PHY:D;CHE:C;BIO:C;BAS:F"
    },
    {
        "CNO":  "0013",
        "SEX":  "M",
        "CANDIDATE-NAME":  "PHILBERTUS MUJUNI",
        "AGGT":  "11",
        "DIV":  "I",
        "DETAILED-SUBJECTS":  "CIV:B;HIS:B;GEO:B;BIB:A;KIS:A;ENG:A;PHY:B;CHE:B;BIO:C;BAS:B"
    },
    {
        "CNO":  "0014",
        "SEX":  "M",
        "CANDIDATE-NAME":  "REMIGIUS ASIMWE",
        "AGGT":  "22",
        "DIV":  "III",
        "DETAILED-SUBJECTS":  "CIV:D;HIS:F;GEO:D;BIB:B;KIS:C;ENG:A;PHY:D;CHE:D;BIO:F;BAS:D"
    },
    {
        "CNO":  "0015",
        "SEX":  "M",
        "CANDIDATE-NAME":  "REVOCATUS BIN\u0027OMUKAMA",
        "AGGT":  "14",
        "DIV":  "I",
        "DETAILED-SUBJECTS":  "CIV:B;HIS:B;GEO:D;BIB:B;KIS:A;ENG:A;PHY:C;CHE:D;BIO:D;BAS:C"
    },
    {
        "CNO":  "0016",
        "SEX":  "M",
        "CANDIDATE-NAME":  "REVOCATUS MWEMEZI",
        "AGGT":  "16",
        "DIV":  "I",
        "DETAILED-SUBJECTS":  "CIV:D;HIS:C;GEO:B;BIB:B;KIS:B;ENG:B;PHY:C;CHE:D;BIO:D;BAS:B"
    },
    {
        "CNO":  "0017",
        "SEX":  "M",
        "CANDIDATE-NAME":  "VALENCE TWEHABURA",
        "AGGT":  "13",
        "DIV":  "I",
        "DETAILED-SUBJECTS":  "CIV:B;HIS:C;GEO:C;BIB:B;KIS:B;ENG:A;PHY:B;CHE:B;BIO:B;BAS:B"
    },
    {
        "CNO":  "0018",
        "SEX":  "M",
        "CANDIDATE-NAME":  "WILLIAM M NJIA",
        "AGGT":  "10",
        "DIV":  "I",
        "DETAILED-SUBJECTS":  "CIV:A;HIS:B;GEO:A;BIB:A;KIS:A;ENG:A;PHY:C;CHE:C;BIO:C;BAS:D"
    },
    {
        "CNO":  "0019",
        "SEX":  "M",
        "CANDIDATE-NAME":  "YUSTINO MUNA",
        "AGGT":  "12",
        "DIV":  "I",
        "DETAILED-SUBJECTS":  "CIV:B;HIS:B;GEO:B;BIB:B;KIS:A;ENG:A;PHY:C;CHE:B;BIO:B;BAS:C"
    }
]
