[
    {
        "CNO":  "P1661/0001",
        "SEX":  "F",
        "AGGT":  "29",
        "DIV":  "IV",
        "DETAILED-SUBJECTS":  "CIV:D;HIST:D;GEO:D;KISW:D;ENGL:D;CHEM:F;BIO:D;B-MATH:F"
    },
    {
        "CNO":  "P1661/0002",
        "SEX":  "F",
        "AGGT":  "33",
        "DIV":  "IV",
        "DETAILED-SUBJECTS":  "CIV:F;HIST:F;GEO:F;KISW:D;ENGL:D;BIO:F;B-MATH:F"
    },
    {
        "CNO":  "P1661/0003",
        "SEX":  "F",
        "AGGT":  "27",
        "DIV":  "IV",
        "DETAILED-SUBJECTS":  "CIV:F;HIST:C;GEO:D;KISW:D;ENGL:D;PHY:F;CHEM:D;BIO:C;B-MATH:F"
    },
    {
        "CNO":  "P1661/0004",
        "SEX":  "M",
        "AGGT":  "34",
        "DIV":  "0",
        "DETAILED-SUBJECTS":  "CIV:F;HIST:F;GEO:F;KISW:D;ENGL:F;CHEM:F;BIO:F;B-MATH:F"
    },
    {
        "CNO":  "P1661/0005",
        "SEX":  "M",
        "AGGT":  "-",
        "DIV":  "0",
        "DETAILED-SUBJECTS":  "CIV:F;HIST:F;GEO:F;KISW:D;ENGL:F;CHEM:X;BIO:F"
    }
]
